FluentWidgets/__init__.py
FluentWidgets/_rc/__init__.py
FluentWidgets/_rc/resources.py
FluentWidgets/common/__init__.py
FluentWidgets/common/fluent_icon.py
FluentWidgets/common/font.py
FluentWidgets/common/splitter.py
FluentWidgets/common/system_tray_icon.py
FluentWidgets/common/tool_info.py
FluentWidgets/components/__init__.py
FluentWidgets/components/layout/__init__.py
FluentWidgets/components/layout/layout.py
FluentWidgets/components/menu/__init__.py
FluentWidgets/components/menu/context_menu_widget.py
FluentWidgets/components/navigation/__init__.py
FluentWidgets/components/navigation/navigation_widget.py
FluentWidgets/components/widgets/__init__.py
FluentWidgets/components/widgets/acrylic_card.py
FluentWidgets/components/widgets/button_card.py
FluentWidgets/components/widgets/combo_box_card.py
FluentWidgets/components/widgets/custom_card.py
FluentWidgets/components/widgets/drag_widget.py
FluentWidgets/components/widgets/expand_group_card.py
FluentWidgets/components/widgets/folder_card.py
FluentWidgets/components/widgets/list_widget.py
FluentWidgets/components/widgets/page_widget.py
FluentWidgets/components/widgets/pips_pager.py
FluentWidgets/components/widgets/scroll_widget.py
FluentWidgets/components/widgets/slider_card.py
FluentWidgets/components/widgets/table_widget.py
FluentWidgets/components/widgets/two_button_card.py
FluentWidgets/components/widgets/view_widget.py
FluentWidgets/components/window/__init__.py
FluentWidgets/components/window/fluent_window.py
FluentWidgets-1.1.5.dist-info/METADATA
FluentWidgets-1.1.5.dist-info/WHEEL
FluentWidgets-1.1.5.dist-info/top_level.txt
FluentWidgets-1.1.5.dist-info/RECORD
