Metadata-Version: 2.1
Name: FluentWidgets
Version: 1.1.5
Author: Mikuas
Author-email: email@example.com
Requires-Dist: PySide6 >=6.4.2
Requires-Dist: PySide6-Fluent-Widgets[full]
